iudicium/__init__.py
iudicium/__main__.py
iudicium/cache.py
iudicium/metrics.py
iudicium/parser.py
iudicium/translators/__init__.py
iudicium/translators/openrouter_translator.py
iudicium/translators/transformers_translator.py
iudicium-0.1.1.dist-info/METADATA
iudicium-0.1.1.dist-info/WHEEL
iudicium-0.1.1.dist-info/entry_points.txt
iudicium-0.1.1.dist-info/RECORD
